setup.cfg
setup.py
wwwoman/WWWoman.py
wwwoman/WWWomanScenario.py
wwwoman/__init__.py
wwwoman.egg-info/PKG-INFO
wwwoman.egg-info/SOURCES.txt
wwwoman.egg-info/dependency_links.txt
wwwoman.egg-info/not-zip-safe
wwwoman.egg-info/requires.txt
wwwoman.egg-info/top_level.txt