Metadata-Version: 1.0
Name: wwwoman
Version: 0.2
Summary: Extension of HTTPretty
Home-page: https://github.com/kavod/WWWoman
Author: Brice GRICHY
Author-email: brice.grichy@gmail.com
License: GPL-3
Platform: UNKNOWN
